pstree_tui/__init__.py
pstree_tui/main.py
pstree_tui-1.4.0.dist-info/METADATA
pstree_tui-1.4.0.dist-info/WHEEL
pstree_tui-1.4.0.dist-info/entry_points.txt
pstree_tui-1.4.0.dist-info/RECORD
