Metadata-Version: 2.4
Name: pstree-tui
Version: 1.4.0
Summary: Interactive collapsible process tree viewer
Project-URL: Repository, https://github.com/bruger/pgtree-collapsible
Author-email: "@readwithai" <talwrii@gmail.com>
License-Expression: MIT
Keywords: curses,pgtree,process,tree,tui
Classifier: Development Status :: 3 - Alpha
Classifier: Environment :: Console :: Curses
Classifier: Intended Audience :: Developers
Classifier: Intended Audience :: System Administrators
Classifier: License :: OSI Approved :: MIT License
Classifier: Operating System :: POSIX :: Linux
Classifier: Programming Language :: Python :: 3
Classifier: Programming Language :: Python :: 3.10
Classifier: Programming Language :: Python :: 3.11
Classifier: Programming Language :: Python :: 3.12
Classifier: Topic :: System :: Monitoring
Classifier: Topic :: Utilities
Requires-Python: >=3.10
